{
  "name": "布兰特",
  "starLevel": 5,
  "stats": {
    "0": {
      "1": {
        "life": 934.0,
        "atk": 30.0,
        "def": 107.0
      },
      "2": {
        "life": 1012.6428,
        "atk": 32.526,
        "def": 115.8061
      },
      "3": {
        "life": 1091.379,
        "atk": 35.055,
        "def": 124.6229
      },
      "4": {
        "life": 1170.1152,
        "atk": 37.584,
        "def": 133.4397
      },
      "5": {
        "life": 1248.758,
        "atk": 40.11,
        "def": 142.2565
      },
      "6": {
        "life": 1327.4942,
        "atk": 42.639,
        "def": 151.0733
      },
      "7": {
        "life": 1406.2304,
        "atk": 45.168,
        "def": 159.8901
      },
      "8": {
        "life": 1484.8732,
        "atk": 47.694,
        "def": 168.7069
      },
      "9": {
        "life": 1563.6094,
        "atk": 50.223,
        "def": 177.5237
      },
      "10": {
        "life": 1642.3456,
        "atk": 52.752,
        "def": 186.3405
      },
      "11": {
        "life": 1720.9884,
        "atk": 55.278,
        "def": 195.1573
      },
      "12": {
        "life": 1799.7246,
        "atk": 57.807,
        "def": 203.9741
      },
      "13": {
        "life": 1878.4608,
        "atk": 60.336,
        "def": 212.7909
      },
      "14": {
        "life": 1957.197,
        "atk": 62.865,
        "def": 221.6077
      },
      "15": {
        "life": 2035.8398,
        "atk": 65.391,
        "def": 230.4245
      },
      "16": {
        "life": 2114.576,
        "atk": 67.92,
        "def": 239.2413
      },
      "17": {
        "life": 2193.3122,
        "atk": 70.449,
        "def": 248.0581
      },
      "18": {
        "life": 2271.955,
        "atk": 72.975,
        "def": 256.8749
      },
      "19": {
        "life": 2350.6912,
        "atk": 75.504,
        "def": 265.6917
      },
      "20": {
        "life": 2429.4274,
        "atk": 78.033,
        "def": 274.5085
      }
    },
    "1": {
      "20": {
        "life": 3052.0318,
        "atk": 100.533,
        "def": 343.8552
      },
      "21": {
        "life": 3130.768,
        "atk": 103.059,
        "def": 352.672
      },
      "22": {
        "life": 3209.5042,
        "atk": 105.588,
        "def": 361.4888
      },
      "23": {
        "life": 3288.147,
        "atk": 108.117,
        "def": 370.3056
      },
      "24": {
        "life": 3366.8832,
        "atk": 110.646,
        "def": 379.1224
      },
      "25": {
        "life": 3445.6194,
        "atk": 113.172,
        "def": 387.9392
      },
      "26": {
        "life": 3524.3556,
        "atk": 115.701,
        "def": 396.756
      },
      "27": {
        "life": 3602.9984,
        "atk": 118.23,
        "def": 405.5728
      },
      "28": {
        "life": 3681.7346,
        "atk": 120.756,
        "def": 414.3896
      },
      "29": {
        "life": 3760.4708,
        "atk": 123.285,
        "def": 423.2064
      },
      "30": {
        "life": 3839.1136,
        "atk": 125.814,
        "def": 432.0232
      },
      "31": {
        "life": 3917.8498,
        "atk": 128.34,
        "def": 440.84
      },
      "32": {
        "life": 3996.586,
        "atk": 130.869,
        "def": 449.6568
      },
      "33": {
        "life": 4075.2288,
        "atk": 133.398,
        "def": 458.4736
      },
      "34": {
        "life": 4153.965,
        "atk": 135.924,
        "def": 467.2904
      },
      "35": {
        "life": 4232.7012,
        "atk": 138.453,
        "def": 476.1072
      },
      "36": {
        "life": 4311.4374,
        "atk": 140.982,
        "def": 484.924
      },
      "37": {
        "life": 4390.0802,
        "atk": 143.511,
        "def": 493.7408
      },
      "38": {
        "life": 4468.8164,
        "atk": 146.037,
        "def": 502.5576
      },
      "39": {
        "life": 4547.5526,
        "atk": 148.566,
        "def": 511.3744
      },
      "40": {
        "life": 4626.1954,
        "atk": 151.095,
        "def": 520.1912
      }
    },
    "2": {
      "40": {
        "life": 5248.8932,
        "atk": 173.595,
        "def": 589.5379
      },
      "41": {
        "life": 5327.6294,
        "atk": 176.121,
        "def": 598.3547
      },
      "42": {
        "life": 5406.2722,
        "atk": 178.65,
        "def": 607.1715
      },
      "43": {
        "life": 5485.0084,
        "atk": 181.179,
        "def": 615.9883
      },
      "44": {
        "life": 5563.7446,
        "atk": 183.705,
        "def": 624.8051
      },
      "45": {
        "life": 5642.3874,
        "atk": 186.234,
        "def": 633.6219
      },
      "46": {
        "life": 5721.1236,
        "atk": 188.763,
        "def": 642.4387
      },
      "47": {
        "life": 5799.8598,
        "atk": 191.292,
        "def": 651.2555
      },
      "48": {
        "life": 5878.596,
        "atk": 193.818,
        "def": 660.0723
      },
      "49": {
        "life": 5957.2388,
        "atk": 196.347,
        "def": 668.8891
      },
      "50": {
        "life": 6035.975,
        "atk": 198.876,
        "def": 677.7059
      }
    },
    "3": {
      "50": {
        "life": 6658.6728,
        "atk": 221.376,
        "def": 747.0526
      },
      "51": {
        "life": 6737.3156,
        "atk": 223.902,
        "def": 755.8694
      },
      "52": {
        "life": 6816.0518,
        "atk": 226.431,
        "def": 764.6862
      },
      "53": {
        "life": 6894.788,
        "atk": 228.96,
        "def": 773.503
      },
      "54": {
        "life": 6973.4308,
        "atk": 231.486,
        "def": 782.3198
      },
      "55": {
        "life": 7052.167,
        "atk": 234.015,
        "def": 791.1366
      },
      "56": {
        "life": 7130.9032,
        "atk": 236.544,
        "def": 799.9534
      },
      "57": {
        "life": 7209.6394,
        "atk": 239.073,
        "def": 808.7702
      },
      "58": {
        "life": 7288.2822,
        "atk": 241.599,
        "def": 817.587
      },
      "59": {
        "life": 7367.0184,
        "atk": 244.128,
        "def": 826.4038
      },
      "60": {
        "life": 7445.7546,
        "atk": 246.657,
        "def": 835.2206
      }
    },
    "4": {
      "60": {
        "life": 8068.359,
        "atk": 269.157,
        "def": 904.578
      },
      "61": {
        "life": 8147.0952,
        "atk": 271.683,
        "def": 913.3948
      },
      "62": {
        "life": 8225.8314,
        "atk": 274.212,
        "def": 922.2116
      },
      "63": {
        "life": 8304.4742,
        "atk": 276.741,
        "def": 931.0284
      },
      "64": {
        "life": 8383.2104,
        "atk": 279.267,
        "def": 939.8452
      },
      "65": {
        "life": 8461.9466,
        "atk": 281.796,
        "def": 948.662
      },
      "66": {
        "life": 8540.5894,
        "atk": 284.325,
        "def": 957.4681
      },
      "67": {
        "life": 8619.3256,
        "atk": 286.851,
        "def": 966.2849
      },
      "68": {
        "life": 8698.0618,
        "atk": 289.38,
        "def": 975.1017
      },
      "69": {
        "life": 8776.798,
        "atk": 291.909,
        "def": 983.9185
      },
      "70": {
        "life": 8855.4408,
        "atk": 294.438,
        "def": 992.7353
      }
    },
    "5": {
      "70": {
        "life": 9478.1386,
        "atk": 309.438,
        "def": 1062.0927
      },
      "71": {
        "life": 9556.8748,
        "atk": 311.964,
        "def": 1070.9095
      },
      "72": {
        "life": 9635.5176,
        "atk": 314.493,
        "def": 1079.7263
      },
      "73": {
        "life": 9714.2538,
        "atk": 317.022,
        "def": 1088.5431
      },
      "74": {
        "life": 9792.99,
        "atk": 319.548,
        "def": 1097.3599
      },
      "75": {
        "life": 9871.6328,
        "atk": 322.077,
        "def": 1106.1767
      },
      "76": {
        "life": 9950.369,
        "atk": 324.606,
        "def": 1114.9935
      },
      "77": {
        "life": 10029.1052,
        "atk": 327.132,
        "def": 1123.8103
      },
      "78": {
        "life": 10107.748,
        "atk": 329.661,
        "def": 1132.6271
      },
      "79": {
        "life": 10186.4842,
        "atk": 332.19,
        "def": 1141.4439
      },
      "80": {
        "life": 10265.2204,
        "atk": 334.719,
        "def": 1150.2607
      }
    },
    "6": {
      "80": {
        "life": 10887.9182,
        "atk": 349.719,
        "def": 1219.6074
      },
      "81": {
        "life": 10966.561,
        "atk": 352.245,
        "def": 1228.4242
      },
      "82": {
        "life": 11045.2972,
        "atk": 354.774,
        "def": 1237.241
      },
      "83": {
        "life": 11124.0334,
        "atk": 357.303,
        "def": 1246.0578
      },
      "84": {
        "life": 11202.6762,
        "atk": 359.829,
        "def": 1254.8746
      },
      "85": {
        "life": 11281.4124,
        "atk": 362.358,
        "def": 1263.6914
      },
      "86": {
        "life": 11360.1486,
        "atk": 364.887,
        "def": 1272.5082
      },
      "87": {
        "life": 11438.7914,
        "atk": 367.413,
        "def": 1281.325
      },
      "88": {
        "life": 11517.5276,
        "atk": 369.942,
        "def": 1290.1418
      },
      "89": {
        "life": 11596.2638,
        "atk": 372.471,
        "def": 1298.9586
      },
      "90": {
        "life": 11675.0,
        "atk": 375.0,
        "def": 1307.7754
      }
    }
  },
  "levelExp": [
    0,
    400,
    400,
    500,
    600,
    700,
    900,
    1000,
    1200,
    1300,
    1500,
    1700,
    2000,
    2200,
    2400,
    2700,
    3000,
    3300,
    3600,
    3900,
    4300,
    4600,
    5000,
    5400,
    5800,
    6300,
    6700,
    7200,
    7700,
    8200,
    8700,
    9300,
    9800,
    10400,
    11000,
    11700,
    12300,
    13000,
    13700,
    14400,
    15100,
    15900,
    16700,
    17500,
    18300,
    19200,
    20000,
    20900,
    21900,
    22800,
    23800,
    24800,
    25800,
    26900,
    28000,
    29100,
    30300,
    31400,
    32600,
    33900,
    35100,
    36400,
    37700,
    39100,
    40500,
    41900,
    43300,
    44800,
    46300,
    47900,
    49500,
    51100,
    52800,
    54500,
    56200,
    58000,
    59800,
    61600,
    63500,
    65400,
    67400,
    69400,
    71400,
    73500,
    75600,
    77800,
    80000,
    82300,
    84600,
    86900,
    105600,
    107400,
    110000,
    113600,
    118600,
    125500,
    134900,
    147300,
    163600,
    184500
  ],
  "skillTree": {
    "1": {
      "skill": {
        "name": "船长的狂想演出",
        "desc": "普攻\n进行最多4段的连续攻击，造成热熔伤害。\n\n重击\n消耗耐力攻击目标，造成热熔伤害。\n\n重击·狂想即兴\n消耗耐力攻击目标，造成热熔伤害。\n·施放普攻第2段或第4段后，长按普攻，可以释放重击·狂想即兴。\n·施放空中攻击第4段后，短按普攻，可以施放重击·狂想即兴。\n\n空中攻击\n进行最多4段连续攻击，造成热熔伤害。空中攻击第1段或第2段按下普攻时，布兰特向目标发起钩索冲荡，触及目标后会向目标发起攻击，若在动作持续期间松开普攻，则会在攻击命中目标后向后空翻；若持续按住，则会持续攻击目标，持续时间结束后，向后空翻。空中攻击第3段攻击后会向后空翻。空中攻击每次空翻后，按下普攻可施放下一段空中攻击，空翻可重置空中闪避次数。\n·若空中攻击第1段钩索冲荡未触及目标，则向前进行一次斩击，造成热熔伤害。\n·若空中攻击第1段或第2段钩索冲荡触及目标，但是发起攻击未命中目标，则会短暂悬停后下落。\n\n闪避反击\n成功闪避后，一定时间内短按普攻，将会攻击目标，造成热熔伤害。",
        "param": [],
        "type": "常态攻击",
        "level": {
          "1": {
            "name": "第一段伤害",
            "param": [
              [
                "25.42%",
                "27.50%",
                "29.59%",
                "32.51%",
                "34.59%",
                "36.99%",
                "40.32%",
                "43.66%",
                "46.99%",
                "50.53%",
                "54.70%",
                "58.87%",
                "63.04%",
                "67.20%",
                "71.37%",
                "75.54%",
                "79.71%",
                "83.88%",
                "88.05%",
                "92.21%"
              ]
            ]
          },
          "2": {
            "name": "第二段伤害",
            "param": [
              [
                "25.50%+25.50%",
                "27.60%+27.60%",
                "29.69%+29.69%",
                "32.61%+32.61%",
                "34.71%+34.71%",
                "37.11%+37.11%",
                "40.46%+40.46%",
                "43.80%+43.80%",
                "47.15%+47.15%",
                "50.70%+50.70%",
                "54.88%+54.88%",
                "59.07%+59.07%",
                "63.25%+63.25%",
                "67.43%+67.43%",
                "71.61%+71.61%",
                "75.79%+75.79%",
                "79.98%+79.98%",
                "84.16%+84.16%",
                "88.34%+88.34%",
                "92.52%+92.52%"
              ]
            ]
          },
          "3": {
            "name": "第三段伤害",
            "param": [
              [
                "11.10%*3+16.64%*2",
                "12.01%*3+18.01%*2",
                "12.92%*3+19.37%*2",
                "14.19%*3+21.28%*2",
                "15.10%*3+22.65%*2",
                "16.15%*3+24.22%*2",
                "17.60%*3+26.40%*2",
                "19.06%*3+28.58%*2",
                "20.51%*3+30.77%*2",
                "22.06%*3+33.08%*2",
                "23.88%*3+35.81%*2",
                "25.70%*3+38.54%*2",
                "27.52%*3+41.27%*2",
                "29.33%*3+44.00%*2",
                "31.15%*3+46.73%*2",
                "32.97%*3+49.46%*2",
                "34.79%*3+52.19%*2",
                "36.61%*3+54.91%*2",
                "38.43%*3+57.64%*2",
                "40.25%*3+60.37%*2"
              ]
            ]
          },
          "4": {
            "name": "第四段伤害",
            "param": [
              [
                "14.10%+11.28%*5",
                "15.25%+12.20%*5",
                "16.41%+13.13%*5",
                "18.03%+14.42%*5",
                "19.18%+15.35%*5",
                "20.51%+16.41%*5",
                "22.36%+17.89%*5",
                "24.21%+19.37%*5",
                "26.06%+20.85%*5",
                "28.02%+22.42%*5",
                "30.33%+24.27%*5",
                "32.65%+26.12%*5",
                "34.96%+27.97%*5",
                "37.27%+29.82%*5",
                "39.58%+31.66%*5",
                "41.89%+33.51%*5",
                "44.20%+35.36%*5",
                "46.51%+37.21%*5",
                "48.82%+39.06%*5",
                "51.14%+40.91%*5"
              ]
            ]
          },
          "5": {
            "name": "重击伤害",
            "param": [
              [
                "99.37%",
                "107.52%",
                "115.67%",
                "127.07%",
                "135.22%",
                "144.59%",
                "157.63%",
                "170.66%",
                "183.70%",
                "197.55%",
                "213.85%",
                "230.14%",
                "246.44%",
                "262.74%",
                "279.03%",
                "295.33%",
                "311.62%",
                "327.92%",
                "344.22%",
                "360.51%"
              ]
            ]
          },
          "6": {
            "name": "重击·狂想即兴伤害",
            "param": [
              [
                "85.00%",
                "91.97%",
                "98.94%",
                "108.70%",
                "115.67%",
                "123.69%",
                "134.84%",
                "145.99%",
                "157.14%",
                "168.99%",
                "182.93%",
                "196.87%",
                "210.81%",
                "224.75%",
                "238.69%",
                "252.63%",
                "266.57%",
                "280.51%",
                "294.45%",
                "308.39%"
              ]
            ]
          },
          "7": {
            "name": "空中攻击第一段伤害",
            "param": [
              [
                "61.80%",
                "66.87%",
                "71.93%",
                "79.03%",
                "84.10%",
                "89.92%",
                "98.03%",
                "106.14%",
                "114.25%",
                "122.86%",
                "132.99%",
                "143.13%",
                "153.26%",
                "163.40%",
                "173.53%",
                "183.67%",
                "193.80%",
                "203.93%",
                "214.07%",
                "224.20%"
              ]
            ]
          },
          "8": {
            "name": "空中攻击第一段长按伤害",
            "param": [
              [
                "16.72%+25.08%+20.90%*6",
                "18.10%+27.14%+22.62%*6",
                "19.47%+29.20%+24.33%*6",
                "21.39%+32.08%+26.73%*6",
                "22.76%+34.13%+28.44%*6",
                "24.33%+36.50%+30.42%*6",
                "26.53%+39.79%+33.16%*6",
                "28.72%+43.08%+35.90%*6",
                "30.91%+46.37%+38.64%*6",
                "33.25%+49.87%+41.56%*6",
                "35.99%+53.98%+44.98%*6",
                "38.73%+58.09%+48.41%*6",
                "41.47%+62.20%+51.84%*6",
                "44.21%+66.32%+55.27%*6",
                "46.96%+70.43%+58.69%*6",
                "49.70%+74.54%+62.12%*6",
                "52.44%+78.66%+65.55%*6",
                "55.18%+82.77%+68.98%*6",
                "57.92%+86.88%+72.40%*6",
                "60.67%+91.00%+75.83%*6"
              ]
            ]
          },
          "9": {
            "name": "空中攻击第一段空翻伤害",
            "param": [
              [
                "17.00%+29.75%",
                "18.40%+32.19%",
                "19.79%+34.63%",
                "21.74%+38.05%",
                "23.14%+40.49%",
                "24.74%+43.29%",
                "26.97%+47.20%",
                "29.20%+51.10%",
                "31.43%+55.00%",
                "33.80%+59.15%",
                "36.59%+64.03%",
                "39.38%+68.91%",
                "42.17%+73.79%",
                "44.95%+78.67%",
                "47.74%+83.55%",
                "50.53%+88.42%",
                "53.32%+93.30%",
                "56.11%+98.18%",
                "58.89%+103.06%",
                "61.68%+107.94%"
              ]
            ]
          },
          "10": {
            "name": "空中攻击第一段斩击伤害",
            "param": [
              [
                "14.17%*3",
                "15.33%*3",
                "16.49%*3",
                "18.12%*3",
                "19.28%*3",
                "20.62%*3",
                "22.48%*3",
                "24.34%*3",
                "26.19%*3",
                "28.17%*3",
                "30.49%*3",
                "32.82%*3",
                "35.14%*3",
                "37.46%*3",
                "39.79%*3",
                "42.11%*3",
                "44.43%*3",
                "46.76%*3",
                "49.08%*3",
                "51.40%*3"
              ]
            ]
          },
          "11": {
            "name": "空中攻击第二段伤害",
            "param": [
              [
                "42.72%+42.72%",
                "46.22%+46.22%",
                "49.72%+49.72%",
                "54.63%+54.63%",
                "58.13%+58.13%",
                "62.16%+62.16%",
                "67.76%+67.76%",
                "73.36%+73.36%",
                "78.97%+78.97%",
                "84.92%+84.92%",
                "91.93%+91.93%",
                "98.93%+98.93%",
                "105.94%+105.94%",
                "112.94%+112.94%",
                "119.95%+119.95%",
                "126.95%+126.95%",
                "133.96%+133.96%",
                "140.96%+140.96%",
                "147.97%+147.97%",
                "154.97%+154.97%"
              ]
            ]
          },
          "12": {
            "name": "空中攻击第二段长按伤害",
            "param": [
              [
                "16.54%*6",
                "17.89%*6",
                "19.25%*6",
                "21.15%*6",
                "22.50%*6",
                "24.06%*6",
                "26.23%*6",
                "28.40%*6",
                "30.57%*6",
                "32.87%*6",
                "35.58%*6",
                "38.30%*6",
                "41.01%*6",
                "43.72%*6",
                "46.43%*6",
                "49.14%*6",
                "51.85%*6",
                "54.56%*6",
                "57.28%*6",
                "59.99%*6"
              ]
            ]
          },
          "13": {
            "name": "空中攻击第二段空翻伤害",
            "param": [
              [
                "17.00%+29.75%",
                "18.40%+32.19%",
                "19.79%+34.63%",
                "21.74%+38.05%",
                "23.14%+40.49%",
                "24.74%+43.29%",
                "26.97%+47.20%",
                "29.20%+51.10%",
                "31.43%+55.00%",
                "33.80%+59.15%",
                "36.59%+64.03%",
                "39.38%+68.91%",
                "42.17%+73.79%",
                "44.95%+78.67%",
                "47.74%+83.55%",
                "50.53%+88.42%",
                "53.32%+93.30%",
                "56.11%+98.18%",
                "58.89%+103.06%",
                "61.68%+107.94%"
              ]
            ]
          },
          "14": {
            "name": "空中攻击第三段伤害",
            "param": [
              [
                "14.17%*6",
                "15.33%*6",
                "16.49%*6",
                "18.12%*6",
                "19.28%*6",
                "20.62%*6",
                "22.48%*6",
                "24.34%*6",
                "26.19%*6",
                "28.17%*6",
                "30.49%*6",
                "32.82%*6",
                "35.14%*6",
                "37.46%*6",
                "39.79%*6",
                "42.11%*6",
                "44.43%*6",
                "46.76%*6",
                "49.08%*6",
                "51.40%*6"
              ]
            ]
          },
          "15": {
            "name": "空中攻击第三段空翻伤害",
            "param": [
              [
                "17.00%+29.75%",
                "18.40%+32.19%",
                "19.79%+34.63%",
                "21.74%+38.05%",
                "23.14%+40.49%",
                "24.74%+43.29%",
                "26.97%+47.20%",
                "29.20%+51.10%",
                "31.43%+55.00%",
                "33.80%+59.15%",
                "36.59%+64.03%",
                "39.38%+68.91%",
                "42.17%+73.79%",
                "44.95%+78.67%",
                "47.74%+83.55%",
                "50.53%+88.42%",
                "53.32%+93.30%",
                "56.11%+98.18%",
                "58.89%+103.06%",
                "61.68%+107.94%"
              ]
            ]
          },
          "16": {
            "name": "空中攻击第四段伤害",
            "param": [
              [
                "51.07%+12.77%*3+38.31%",
                "55.26%+13.82%*3+41.45%",
                "59.45%+14.87%*3+44.59%",
                "65.31%+16.33%*3+48.98%",
                "69.50%+17.38%*3+52.13%",
                "74.31%+18.58%*3+55.74%",
                "81.01%+20.26%*3+60.76%",
                "87.71%+21.93%*3+65.79%",
                "94.41%+23.61%*3+70.81%",
                "101.53%+25.39%*3+76.15%",
                "109.91%+27.48%*3+82.43%",
                "118.28%+29.57%*3+88.71%",
                "126.66%+31.67%*3+95.00%",
                "135.03%+33.76%*3+101.28%",
                "143.41%+35.86%*3+107.56%",
                "151.78%+37.95%*3+113.84%",
                "160.16%+40.04%*3+120.12%",
                "168.53%+42.14%*3+126.40%",
                "176.91%+44.23%*3+132.68%",
                "185.28%+46.32%*3+138.96%"
              ]
            ]
          },
          "17": {
            "name": "闪避反击伤害",
            "param": [
              [
                "19.13%*3+28.69%*2",
                "20.70%*3+31.04%*2",
                "22.27%*3+33.40%*2",
                "24.46%*3+36.69%*2",
                "26.03%*3+39.04%*2",
                "27.83%*3+41.75%*2",
                "30.34%*3+45.51%*2",
                "32.85%*3+49.28%*2",
                "35.36%*3+53.04%*2",
                "38.03%*3+57.04%*2",
                "41.16%*3+61.74%*2",
                "44.30%*3+66.45%*2",
                "47.44%*3+71.15%*2",
                "50.57%*3+75.86%*2",
                "53.71%*3+80.56%*2",
                "56.85%*3+85.27%*2",
                "59.98%*3+89.97%*2",
                "63.12%*3+94.68%*2",
                "66.26%*3+99.38%*2",
                "69.39%*3+104.09%*2"
              ]
            ]
          },
          "18": {
            "name": "重击耐力消耗",
            "param": [
              [
                "25",
                "25",
                "25",
                "25",
                "25",
                "25",
                "25",
                "25",
                "25",
                "25",
                "25",
                "25",
                "25",
                "25",
                "25",
                "25",
                "25",
                "25",
                "25",
                "25"
              ]
            ]
          },
          "19": {
            "name": "重击·狂想即兴耐力消耗",
            "param": [
              [
                "25",
                "25",
                "25",
                "25",
                "25",
                "25",
                "25",
                "25",
                "25",
                "25",
                "25",
                "25",
                "25",
                "25",
                "25",
                "25",
                "25",
                "25",
                "25",
                "25"
              ]
            ]
          },
          "20": {
            "name": "空中攻击耐力消耗",
            "param": [
              [
                "5",
                "5",
                "5",
                "5",
                "5",
                "5",
                "5",
                "5",
                "5",
                "5",
                "5",
                "5",
                "5",
                "5",
                "5",
                "5",
                "5",
                "5",
                "5",
                "5"
              ]
            ]
          },
          "21": {
            "name": "空中攻击长按耐力消耗",
            "param": [
              [
                "15",
                "15",
                "15",
                "15",
                "15",
                "15",
                "15",
                "15",
                "15",
                "15",
                "15",
                "15",
                "15",
                "15",
                "15",
                "15",
                "15",
                "15",
                "15",
                "15"
              ]
            ]
          }
        }
      }
    },
    "2": {
      "skill": {
        "name": "起锚！",
        "desc": "布兰特将自己弹飞至空中，并对范围内的目标造成热熔伤害。处于空中时，若【喝彩】未充满，共鸣技能起锚！替换为空中下落攻击\n\n空中下落攻击\n消耗耐力进行空中下落攻击，造成热熔伤害，此次伤害为普攻伤害。\n·空中攻击第1段钩索冲荡未触及目标，向前斩击后，可以短按普攻施放空中下落攻击。\n·空中攻击第1段或第2段钩索冲荡触及目标，但是发起攻击未命中后，可以在悬停期间短按普攻施放空中下落攻击。\n",
        "param": [],
        "type": "共鸣技能",
        "level": {
          "1": {
            "name": "技能伤害",
            "param": [
              [
                "100.77%+67.18%",
                "109.04%+72.69%",
                "117.30%+78.20%",
                "128.87%+85.91%",
                "137.13%+91.42%",
                "146.64%+97.76%",
                "159.86%+106.57%",
                "173.08%+115.39%",
                "186.30%+124.20%",
                "200.35%+133.57%",
                "216.87%+144.58%",
                "233.40%+155.60%",
                "249.92%+166.62%",
                "266.45%+177.64%",
                "282.98%+188.65%",
                "299.50%+199.67%",
                "316.03%+210.69%",
                "332.56%+221.71%",
                "349.08%+232.72%",
                "365.61%+243.74%"
              ]
            ]
          },
          "2": {
            "name": "下落攻击伤害",
            "param": [
              [
                "52.70%",
                "57.03%",
                "61.35%",
                "67.40%",
                "71.72%",
                "76.69%",
                "83.60%",
                "90.52%",
                "97.43%",
                "104.78%",
                "113.42%",
                "122.06%",
                "130.71%",
                "139.35%",
                "147.99%",
                "156.63%",
                "165.28%",
                "173.92%",
                "182.56%",
                "191.21%"
              ]
            ]
          },
          "3": {
            "name": "下落攻击耐力消耗",
            "param": [
              [
                "30",
                "30",
                "30",
                "30",
                "30",
                "30",
                "30",
                "30",
                "30",
                "30",
                "30",
                "30",
                "30",
                "30",
                "30",
                "30",
                "30",
                "30",
                "30",
                "30"
              ]
            ]
          },
          "4": {
            "name": "冷却时间",
            "param": [
              [
                "4",
                "4",
                "4",
                "4",
                "4",
                "4",
                "4",
                "4",
                "4",
                "4",
                "4",
                "4",
                "4",
                "4",
                "4",
                "4",
                "4",
                "4",
                "4",
                "4"
              ]
            ]
          },
          "5": {
            "name": "回复协奏能量",
            "param": [
              [
                "10",
                "10",
                "10",
                "10",
                "10",
                "10",
                "10",
                "10",
                "10",
                "10",
                "10",
                "10",
                "10",
                "10",
                "10",
                "10",
                "10",
                "10",
                "10",
                "10"
              ]
            ]
          }
        }
      }
    },
    "3": {
      "skill": {
        "name": "直到世界尽头",
        "desc": "对范围内的目标造成热熔伤害，并回复附近队伍所有角色的生命值，施放结束后进入燃焰状态。\n可以在空中施放。\n\n燃焰\n常态攻击、共鸣技能起锚！命中时获取【喝彩】效率提升{1}。共鸣回路戏中人生替换为「我」的人生。\n\n「我」的人生\n布兰特基于共鸣效率获得额外攻击：当自身共鸣效率大于{2}时，每超过{3}的共鸣效率计算为{4}点攻击提升，上限为{5}。\n",
        "param": [
          "12",
          "100%",
          "150%",
          "1%",
          "20",
          "2600"
        ],
        "type": "共鸣解放",
        "level": {
          "1": {
            "name": "技能伤害",
            "param": [
              [
                "42.78%*4+171.12%",
                "46.29%*4+185.16%",
                "49.80%*4+199.19%",
                "54.71%*4+218.83%",
                "58.22%*4+232.87%",
                "62.25%*4+249.00%",
                "67.87%*4+271.45%",
                "73.48%*4+293.90%",
                "79.09%*4+316.35%",
                "85.06%*4+340.21%",
                "92.07%*4+368.27%",
                "99.09%*4+396.34%",
                "106.10%*4+424.40%",
                "113.12%*4+452.46%",
                "120.14%*4+480.53%",
                "127.15%*4+508.59%",
                "134.17%*4+536.65%",
                "141.18%*4+564.72%",
                "148.20%*4+592.78%",
                "155.22%*4+620.85%"
              ]
            ]
          },
          "2": {
            "name": "治疗量",
            "param": [
              [
                "500+1.75",
                "560+1.96",
                "625+2.18",
                "700+2.45",
                "790+2.76",
                "875+3.06",
                "890+3.11",
                "910+3.18",
                "925+3.23",
                "950+3.32",
                "1028+3.59",
                "1106+3.87",
                "1185+4.14",
                "1263+4.42",
                "1341+4.69",
                "1420+4.97",
                "1498+5.24",
                "1576+5.51",
                "1655+5.79",
                "1733+6.06"
              ]
            ]
          },
          "3": {
            "name": "燃焰状态持续时间",
            "param": [
              [
                "12",
                "12",
                "12",
                "12",
                "12",
                "12",
                "12",
                "12",
                "12",
                "12",
                "12",
                "12",
                "12",
                "12",
                "12",
                "12",
                "12",
                "12",
                "12",
                "12"
              ]
            ]
          },
          "4": {
            "name": "冷却时间",
            "param": [
              [
                "24",
                "24",
                "24",
                "24",
                "24",
                "24",
                "24",
                "24",
                "24",
                "24",
                "24",
                "24",
                "24",
                "24",
                "24",
                "24",
                "24",
                "24",
                "24",
                "24"
              ]
            ]
          },
          "5": {
            "name": "消耗共鸣能量",
            "param": [
              [
                "175",
                "175",
                "175",
                "175",
                "175",
                "175",
                "175",
                "175",
                "175",
                "175",
                "175",
                "175",
                "175",
                "175",
                "175",
                "175",
                "175",
                "175",
                "175",
                "175"
              ]
            ]
          },
          "6": {
            "name": "回复协奏能量",
            "param": [
              [
                "20",
                "20",
                "20",
                "20",
                "20",
                "20",
                "20",
                "20",
                "20",
                "20",
                "20",
                "20",
                "20",
                "20",
                "20",
                "20",
                "20",
                "20",
                "20",
                "20"
              ]
            ]
          }
        }
      }
    },
    "4": {
      "skill": {
        "name": "领航之焰",
        "desc": "涛声喝彩的治疗量提升{0}。",
        "param": [
          "20%"
        ],
        "type": "固有技能",
        "level": {}
      }
    },
    "5": {
      "skill": {
        "name": "迎海投火的决意",
        "desc": "布兰特空中攻击抗打断提升，热熔伤害加成提升{0}。",
        "param": [
          "15%"
        ],
        "type": "固有技能",
        "level": {}
      }
    },
    "6": {
      "skill": {
        "name": "为我！",
        "desc": "攻击目标，造成热熔伤害，并获得幕间掌声效果。\n\n幕间掌声\n下一次空中攻击从第2段开始，提前落地后或切换至其他角色失去该效果。",
        "param": [],
        "type": "变奏技能",
        "level": {
          "2": {
            "name": "技能伤害",
            "param": [
              [
                "102.00%+25.50%",
                "110.37%+27.60%",
                "118.73%+29.69%",
                "130.44%+32.61%",
                "138.81%+34.71%",
                "148.43%+37.11%",
                "161.81%+40.46%",
                "175.19%+43.80%",
                "188.57%+47.15%",
                "202.79%+50.70%",
                "219.52%+54.88%",
                "236.25%+59.07%",
                "252.98%+63.25%",
                "269.70%+67.43%",
                "286.43%+71.61%",
                "303.16%+75.79%",
                "319.89%+79.98%",
                "336.62%+84.16%",
                "353.34%+88.34%",
                "370.07%+92.52%"
              ]
            ]
          },
          "3": {
            "name": "回复协奏能量",
            "param": [
              [
                "10",
                "10",
                "10",
                "10",
                "10",
                "10",
                "10",
                "10",
                "10",
                "10",
                "10",
                "10",
                "10",
                "10",
                "10",
                "10",
                "10",
                "10",
                "10",
                "10"
              ]
            ]
          }
        }
      }
    },
    "7": {
      "skill": {
        "name": "海中戏剧",
        "desc": "戏中人生\n布兰特基于共鸣效率获得额外攻击：当自身共鸣效率大于{0}时，每超过1%的共鸣效率计算为{1}点攻击提升，上限为{2}。\n\n涛声喝彩\n当【喝彩】达到{3}、{4}、{5}、{6}点后，会回复附近队伍所有角色的生命值。\n\n火焰归亡曲\n当【喝彩】充满，共鸣技能起锚！替换为火焰归亡曲。\n施放火焰归亡曲时，消耗全部【喝彩】，造成热熔伤害，此次伤害为普攻伤害，并获得护盾。若在燃焰状态中施放，则在火焰归亡曲结束后失去燃焰状态。\n\n喝彩获取规则\n【喝彩】上限{7}点。\n常态攻击命中目标时，获得【喝彩】。\n变奏技能命中目标时，获得【喝彩】。\n共鸣技能命中目标时，获得【喝彩】。",
        "param": [
          "150%",
          "12",
          "1560",
          "25",
          "50",
          "75",
          "100",
          "100"
        ],
        "type": "共鸣回路",
        "level": {
          "1": {
            "name": "火焰归亡曲伤害",
            "param": [
              [
                "23.75%*2+47.50%+95.00%*2+665.00%",
                "25.70%*2+51.40%+102.79%*2+719.53%",
                "27.65%*2+55.29%+110.58%*2+774.06%",
                "30.38%*2+60.75%+121.49%*2+850.41%",
                "32.32%*2+64.64%+129.28%*2+904.94%",
                "34.56%*2+69.12%+138.24%*2+967.65%",
                "37.68%*2+75.35%+150.70%*2+1054.89%",
                "40.80%*2+81.59%+163.17%*2+1142.14%",
                "43.91%*2+87.82%+175.63%*2+1229.39%",
                "47.22%*2+94.44%+188.87%*2+1322.09%",
                "51.12%*2+102.23%+204.45%*2+1431.15%",
                "55.01%*2+110.02%+220.03%*2+1540.21%",
                "58.91%*2+117.81%+235.61%*2+1649.27%",
                "62.80%*2+125.60%+251.19%*2+1758.33%",
                "66.70%*2+133.39%+266.77%*2+1867.39%",
                "70.59%*2+141.18%+282.35%*2+1976.45%",
                "74.49%*2+148.97%+297.93%*2+2085.51%",
                "78.38%*2+156.76%+313.51%*2+2194.57%",
                "82.28%*2+164.55%+329.09%*2+2303.63%",
                "86.17%*2+172.34%+344.67%*2+2412.69%"
              ]
            ]
          },
          "2": {
            "name": "涛声喝彩治疗量",
            "param": [
              [
                "312+1.09",
                "350+1.22",
                "390+1.36",
                "437+1.53",
                "493+1.72",
                "546+1.91",
                "556+1.94",
                "568+1.99",
                "578+2.02",
                "593+2.07",
                "642+2.24",
                "691+2.42",
                "740+2.59",
                "789+2.76",
                "838+2.93",
                "887+3.1",
                "936+3.27",
                "985+3.44",
                "1034+3.62",
                "1083+3.79"
              ]
            ]
          },
          "3": {
            "name": "护盾量",
            "param": [
              [
                "2500+9",
                "2800+10.08",
                "3125+11.25",
                "3500+12.6",
                "3950+14.22",
                "4375+15.75",
                "4450+16.02",
                "4550+16.38",
                "4625+16.65",
                "4750+17.1",
                "5141+18.51",
                "5533+19.92",
                "5925+21.33",
                "6317+22.74",
                "6709+24.15",
                "7100+25.56",
                "7492+26.97",
                "7884+28.38",
                "8276+29.79",
                "8668+31.2"
              ]
            ]
          },
          "4": {
            "name": "护盾持续时间",
            "param": [
              [
                "30",
                "30",
                "30",
                "30",
                "30",
                "30",
                "30",
                "30",
                "30",
                "30",
                "30",
                "30",
                "30",
                "30",
                "30",
                "30",
                "30",
                "30",
                "30",
                "30"
              ]
            ]
          },
          "5": {
            "name": "火焰归亡曲回复协奏能量",
            "param": [
              [
                "20",
                "20",
                "20",
                "20",
                "20",
                "20",
                "20",
                "20",
                "20",
                "20",
                "20",
                "20",
                "20",
                "20",
                "20",
                "20",
                "20",
                "20",
                "20",
                "20"
              ]
            ]
          }
        }
      }
    },
    "8": {
      "skill": {
        "name": "航向确定！",
        "desc": "下一位登场角色热熔伤害加深{0}，共鸣技能伤害加深{1}，效果持续{2}秒，若切换至其他角色则该效果提前结束。",
        "param": [
          "20%",
          "25%",
          "14"
        ],
        "type": "延奏技能",
        "level": {}
      }
    },
    "9": {
      "skill": {
        "name": "暴击提升",
        "desc": "暴击提升{0}",
        "param": [
          "1.20%"
        ]
      }
    },
    "10": {
      "skill": {
        "name": "攻击提升",
        "desc": "攻击提升{0}",
        "param": [
          "1.80%"
        ]
      }
    },
    "11": {
      "skill": {
        "name": "攻击提升",
        "desc": "攻击提升{0}",
        "param": [
          "1.80%"
        ]
      }
    },
    "12": {
      "skill": {
        "name": "暴击提升",
        "desc": "暴击提升{0}",
        "param": [
          "1.20%"
        ]
      }
    },
    "13": {
      "skill": {
        "name": "暴击提升",
        "desc": "暴击提升{0}",
        "param": [
          "2.80%"
        ]
      }
    },
    "14": {
      "skill": {
        "name": "攻击提升",
        "desc": "攻击提升{0}",
        "param": [
          "4.20%"
        ]
      }
    },
    "15": {
      "skill": {
        "name": "攻击提升",
        "desc": "攻击提升{0}",
        "param": [
          "4.20%"
        ]
      }
    },
    "16": {
      "skill": {
        "name": "暴击提升",
        "desc": "暴击提升{0}",
        "param": [
          "2.80%"
        ]
      }
    }
  },
  "chains": {
    "1": {
      "name": "跟随洋流和信风",
      "desc": "火焰归亡曲施放期间会短暂停滞周围的目标，若在此期间切换至其他角色则提前结束停滞效果。\n施放变奏技能为我！后或每次空中攻击空翻时，布兰特造成伤害提升{0}，持续{1}秒，可叠加{2}层。",
      "param": [
        "20%",
        "5",
        "3"
      ]
    },
    "2": {
      "name": "掠夺欢声与笑颜",
      "desc": "施放空中攻击和火焰归亡曲时暴击提升{0}。\n布兰特延奏技能航向确定！获得额外效果，{2}秒内：\n下一位登场角色或附近队伍中激活布兰特延奏技能的角色施放共鸣技能命中目标时，布兰特将攻击目标，会产生一次爆炸，造成布兰特攻击{1}的热熔伤害，此次伤害为普攻伤害。爆炸每秒可触发{3}次，最多可触发{4}次爆炸。\n·切换至其他角色会保留该额外效果。",
      "param": [
        "30%",
        "440%",
        "20",
        "1",
        "2"
      ]
    },
    "3": {
      "name": "无惧惊涛骇浪",
      "desc": "火焰归亡曲伤害倍率提升{0}。",
      "param": [
        "42%"
      ]
    },
    "4": {
      "name": "纵情放声歌唱",
      "desc": "火焰归亡曲获得的护盾量提升{0}，布兰特施放火焰归亡曲时，会回复附近队伍所有角色的生命值（每{1}的共鸣效率回复{2}点生命值）。",
      "param": [
        "20%",
        "1%",
        "6.60"
      ]
    },
    "5": {
      "name": "演员说：生活皆舞台",
      "desc": "造成普攻伤害时，普攻伤害加成提升{0}，持续{1}秒。",
      "param": [
        "15%",
        "10"
      ]
    },
    "6": {
      "name": "船长答：狂欢即世界！",
      "desc": "空中攻击的倍率提升{0}。\n施放火焰归亡曲后，会在原地产生一次再燃，造成等同于火焰归亡曲{1}的热熔伤害，此次伤害为普攻伤害。",
      "param": [
        "30%",
        "30%"
      ]
    }
  }
}