{
  "name": "奥古斯塔",
  "attributeId": 3,
  "weaponTypeId": 1,
  "starLevel": 5,
  "stats": {
    "0": {
      "1": {
        "life": 824.0,
        "atk": 37.0,
        "def": 91.0
      },
      "2": {
        "life": 893.3808,
        "atk": 40.1154,
        "def": 98.4893
      },
      "3": {
        "life": 962.844,
        "atk": 43.2345,
        "def": 105.9877
      },
      "4": {
        "life": 1032.3072,
        "atk": 46.3536,
        "def": 113.4861
      },
      "5": {
        "life": 1101.688,
        "atk": 49.469,
        "def": 120.9845
      },
      "6": {
        "life": 1171.1512,
        "atk": 52.5881,
        "def": 128.4829
      },
      "7": {
        "life": 1240.6144,
        "atk": 55.7072,
        "def": 135.9813
      },
      "8": {
        "life": 1309.9952,
        "atk": 58.8226,
        "def": 143.4797
      },
      "9": {
        "life": 1379.4584,
        "atk": 61.9417,
        "def": 150.9781
      },
      "10": {
        "life": 1448.9216,
        "atk": 65.0608,
        "def": 158.4765
      },
      "11": {
        "life": 1518.3024,
        "atk": 68.1762,
        "def": 165.9749
      },
      "12": {
        "life": 1587.7656,
        "atk": 71.2953,
        "def": 173.4733
      },
      "13": {
        "life": 1657.2288,
        "atk": 74.4144,
        "def": 180.9717
      },
      "14": {
        "life": 1726.692,
        "atk": 77.5335,
        "def": 188.4701
      },
      "15": {
        "life": 1796.0728,
        "atk": 80.6489,
        "def": 195.9685
      },
      "16": {
        "life": 1865.536,
        "atk": 83.768,
        "def": 203.4669
      },
      "17": {
        "life": 1934.9992,
        "atk": 86.8871,
        "def": 210.9653
      },
      "18": {
        "life": 2004.38,
        "atk": 90.0025,
        "def": 218.4637
      },
      "19": {
        "life": 2073.8432,
        "atk": 93.1216,
        "def": 225.9621
      },
      "20": {
        "life": 2143.3064,
        "atk": 96.2407,
        "def": 233.4605
      }
    },
    "1": {
      "20": {
        "life": 2692.5848,
        "atk": 123.9907,
        "def": 292.4376
      },
      "21": {
        "life": 2762.048,
        "atk": 127.1061,
        "def": 299.936
      },
      "22": {
        "life": 2831.5112,
        "atk": 130.2252,
        "def": 307.4344
      },
      "23": {
        "life": 2900.892,
        "atk": 133.3443,
        "def": 314.9328
      },
      "24": {
        "life": 2970.3552,
        "atk": 136.4634,
        "def": 322.4312
      },
      "25": {
        "life": 3039.8184,
        "atk": 139.5788,
        "def": 329.9296
      },
      "26": {
        "life": 3109.2816,
        "atk": 142.6979,
        "def": 337.428
      },
      "27": {
        "life": 3178.6624,
        "atk": 145.817,
        "def": 344.9264
      },
      "28": {
        "life": 3248.1256,
        "atk": 148.9324,
        "def": 352.4248
      },
      "29": {
        "life": 3317.5888,
        "atk": 152.0515,
        "def": 359.9232
      },
      "30": {
        "life": 3386.9696,
        "atk": 155.1706,
        "def": 367.4216
      },
      "31": {
        "life": 3456.4328,
        "atk": 158.286,
        "def": 374.92
      },
      "32": {
        "life": 3525.896,
        "atk": 161.4051,
        "def": 382.4184
      },
      "33": {
        "life": 3595.2768,
        "atk": 164.5242,
        "def": 389.9168
      },
      "34": {
        "life": 3664.74,
        "atk": 167.6396,
        "def": 397.4152
      },
      "35": {
        "life": 3734.2032,
        "atk": 170.7587,
        "def": 404.9136
      },
      "36": {
        "life": 3803.6664,
        "atk": 173.8778,
        "def": 412.412
      },
      "37": {
        "life": 3873.0472,
        "atk": 176.9969,
        "def": 419.9104
      },
      "38": {
        "life": 3942.5104,
        "atk": 180.1123,
        "def": 427.4088
      },
      "39": {
        "life": 4011.9736,
        "atk": 183.2314,
        "def": 434.9072
      },
      "40": {
        "life": 4081.3544,
        "atk": 186.3505,
        "def": 442.4056
      }
    },
    "2": {
      "40": {
        "life": 4630.7152,
        "atk": 214.1005,
        "def": 501.3827
      },
      "41": {
        "life": 4700.1784,
        "atk": 217.2159,
        "def": 508.8811
      },
      "42": {
        "life": 4769.5592,
        "atk": 220.335,
        "def": 516.3795
      },
      "43": {
        "life": 4839.0224,
        "atk": 223.4541,
        "def": 523.8779
      },
      "44": {
        "life": 4908.4856,
        "atk": 226.5695,
        "def": 531.3763
      },
      "45": {
        "life": 4977.8664,
        "atk": 229.6886,
        "def": 538.8747
      },
      "46": {
        "life": 5047.3296,
        "atk": 232.8077,
        "def": 546.3731
      },
      "47": {
        "life": 5116.7928,
        "atk": 235.9268,
        "def": 553.8715
      },
      "48": {
        "life": 5186.256,
        "atk": 239.0422,
        "def": 561.3699
      },
      "49": {
        "life": 5255.6368,
        "atk": 242.1613,
        "def": 568.8683
      },
      "50": {
        "life": 5325.1,
        "atk": 245.2804,
        "def": 576.3667
      }
    },
    "3": {
      "50": {
        "life": 5874.4608,
        "atk": 273.0304,
        "def": 635.3438
      },
      "51": {
        "life": 5943.8416,
        "atk": 276.1458,
        "def": 642.8422
      },
      "52": {
        "life": 6013.3048,
        "atk": 279.2649,
        "def": 650.3406
      },
      "53": {
        "life": 6082.768,
        "atk": 282.384,
        "def": 657.839
      },
      "54": {
        "life": 6152.1488,
        "atk": 285.4994,
        "def": 665.3374
      },
      "55": {
        "life": 6221.612,
        "atk": 288.6185,
        "def": 672.8358
      },
      "56": {
        "life": 6291.0752,
        "atk": 291.7376,
        "def": 680.3342
      },
      "57": {
        "life": 6360.5384,
        "atk": 294.8567,
        "def": 687.8326
      },
      "58": {
        "life": 6429.9192,
        "atk": 297.9721,
        "def": 695.331
      },
      "59": {
        "life": 6499.3824,
        "atk": 301.0912,
        "def": 702.8294
      },
      "60": {
        "life": 6568.8456,
        "atk": 304.2103,
        "def": 710.3278
      }
    },
    "4": {
      "60": {
        "life": 7118.124,
        "atk": 331.9603,
        "def": 769.314
      },
      "61": {
        "life": 7187.5872,
        "atk": 335.0757,
        "def": 776.8124
      },
      "62": {
        "life": 7257.0504,
        "atk": 338.1948,
        "def": 784.3108
      },
      "63": {
        "life": 7326.4312,
        "atk": 341.3139,
        "def": 791.8092
      },
      "64": {
        "life": 7395.8944,
        "atk": 344.4293,
        "def": 799.3076
      },
      "65": {
        "life": 7465.3576,
        "atk": 347.5484,
        "def": 806.806
      },
      "66": {
        "life": 7534.7384,
        "atk": 350.6675,
        "def": 814.2953
      },
      "67": {
        "life": 7604.2016,
        "atk": 353.7829,
        "def": 821.7937
      },
      "68": {
        "life": 7673.6648,
        "atk": 356.902,
        "def": 829.2921
      },
      "69": {
        "life": 7743.128,
        "atk": 360.0211,
        "def": 836.7905
      },
      "70": {
        "life": 7812.5088,
        "atk": 363.1402,
        "def": 844.2889
      }
    },
    "5": {
      "70": {
        "life": 8361.8696,
        "atk": 381.6402,
        "def": 903.2751
      },
      "71": {
        "life": 8431.3328,
        "atk": 384.7556,
        "def": 910.7735
      },
      "72": {
        "life": 8500.7136,
        "atk": 387.8747,
        "def": 918.2719
      },
      "73": {
        "life": 8570.1768,
        "atk": 390.9938,
        "def": 925.7703
      },
      "74": {
        "life": 8639.64,
        "atk": 394.1092,
        "def": 933.2687
      },
      "75": {
        "life": 8709.0208,
        "atk": 397.2283,
        "def": 940.7671
      },
      "76": {
        "life": 8778.484,
        "atk": 400.3474,
        "def": 948.2655
      },
      "77": {
        "life": 8847.9472,
        "atk": 403.4628,
        "def": 955.7639
      },
      "78": {
        "life": 8917.328,
        "atk": 406.5819,
        "def": 963.2623
      },
      "79": {
        "life": 8986.7912,
        "atk": 409.701,
        "def": 970.7607
      },
      "80": {
        "life": 9056.2544,
        "atk": 412.8201,
        "def": 978.2591
      }
    },
    "6": {
      "80": {
        "life": 9605.6152,
        "atk": 431.3201,
        "def": 1037.2362
      },
      "81": {
        "life": 9674.996,
        "atk": 434.4355,
        "def": 1044.7346
      },
      "82": {
        "life": 9744.4592,
        "atk": 437.5546,
        "def": 1052.233
      },
      "83": {
        "life": 9813.9224,
        "atk": 440.6737,
        "def": 1059.7314
      },
      "84": {
        "life": 9883.3032,
        "atk": 443.7891,
        "def": 1067.2298
      },
      "85": {
        "life": 9952.7664,
        "atk": 446.9082,
        "def": 1074.7282
      },
      "86": {
        "life": 10022.2296,
        "atk": 450.0273,
        "def": 1082.2266
      },
      "87": {
        "life": 10091.6104,
        "atk": 453.1427,
        "def": 1089.725
      },
      "88": {
        "life": 10161.0736,
        "atk": 456.2618,
        "def": 1097.2234
      },
      "89": {
        "life": 10230.5368,
        "atk": 459.3809,
        "def": 1104.7218
      },
      "90": {
        "life": 10300.0,
        "atk": 462.5,
        "def": 1112.2202
      }
    }
  },
  "skillTree": {
    "1": {
      "skill": {
        "name": "逐狩",
        "desc": "普攻\n进行最多4段的连续攻击，造成导电伤害。\n\n重击·鸣铁\n消耗耐力攻击目标，造成导电伤害。施放后短时间内短按普攻，可以施放普攻第2段。\n\n空中攻击\n消耗耐力进行空中下落攻击，造成导电伤害。\n\n闪避反击\n成功闪避后一定时间内短按普攻，将会攻击目标，造成导电伤害。\n\n空中闪避反击\n空中成功闪避后一定时间内短按普攻，消耗耐力进行空中下落攻击，造成导电伤害。\n\n重击·烁雷·后撤\n【战势】满时，重击·鸣铁替换为重击·烁雷·后撤，造成导电伤害，施放时消耗全部的【战势】。\n·技能施放时，一定时间后松开普攻，或者再次短按普攻，可以施放重击·烁雷·旋切。\n·技能被打断后一定时间内若没有离开地面，亦可施放重击·烁雷·旋切。\n\n重击·烁雷·旋切\n奥古斯塔舞剑旋转，造成导电伤害。\n\n重击·烁雷·升拳\n【战势】满时，短按跳跃可以施放重击·烁雷·升拳，造成导电伤害，施放时消耗全部的【战势】。\n当施放共鸣技能·斩锋时，若【战势】满，短按共鸣技能或跳跃可以施放重击·烁雷·升拳，造成导电伤害，施放时消耗全部的【战势】。\n当施放重击·鸣铁或闪避反击·重击·鸣铁时，若【战势】满，一定时间后松开普攻，或者再次短按普攻或跳跃可以施放重击·烁雷·升拳，造成导电伤害，施放时消耗全部的【战势】。\n\n闪避反击·重击·鸣铁\n【战势】满时，闪避反击替换为闪避反击·重击·鸣铁，造成导电伤害，此次伤害为重击伤害。\n\n闪避反击·烁雷·后撤\n【权炳】满时，地面闪避成功后短按普攻，闪避反击与闪避反击·重击·鸣铁替换为闪避反击·烁雷·后撤，施放时造成导电伤害，此次伤害为重击伤害。\n·技能施放时，一定时间后松开普攻，或者再次短按普攻，可以施放重击·烁雷·旋切。\n·技能被打断后一定时间内若没有离开地面，亦可施放重击·烁雷·旋切。\n\n【战势】获取规则\n【战势】上限为{0}点。\n·普攻、重击·鸣铁、空中攻击、空中闪避反击、共鸣技能·斩锋、闪避反击、闪避反击·重击·鸣铁造成伤害时可以获得【战势】。\n·施放变奏技能·灼金的巡行时，回满【战势】。",
        "param": [
          "100"
        ],
        "type": "常态攻击",
        "level": {
          "1": {
            "name": "第一段伤害",
            "param": [
              [
                "28.90%",
                "31.27%",
                "33.64%",
                "36.96%",
                "39.33%",
                "42.06%",
                "45.85%",
                "49.64%",
                "53.43%",
                "57.46%",
                "62.20%",
                "66.94%",
                "71.68%",
                "76.42%",
                "81.16%",
                "85.90%",
                "90.64%",
                "95.38%",
                "100.12%",
                "104.86%"
              ]
            ]
          },
          "2": {
            "name": "第二段伤害",
            "param": [
              [
                "33.70%*2",
                "36.47%*2",
                "39.23%*2",
                "43.10%*2",
                "45.86%*2",
                "49.04%*2",
                "53.46%*2",
                "57.88%*2",
                "62.31%*2",
                "67.00%*2",
                "72.53%*2",
                "78.06%*2",
                "83.58%*2",
                "89.11%*2",
                "94.64%*2",
                "100.16%*2",
                "105.69%*2",
                "111.22%*2",
                "116.75%*2",
                "122.27%*2"
              ]
            ]
          },
          "3": {
            "name": "第三段伤害",
            "param": [
              [
                "33.00%*3",
                "35.71%*3",
                "38.42%*3",
                "42.21%*3",
                "44.91%*3",
                "48.02%*3",
                "52.35%*3",
                "56.68%*3",
                "61.01%*3",
                "65.61%*3",
                "71.02%*3",
                "76.44%*3",
                "81.85%*3",
                "87.26%*3",
                "92.67%*3",
                "98.08%*3",
                "103.50%*3",
                "108.91%*3",
                "114.32%*3",
                "119.73%*3"
              ]
            ]
          },
          "4": {
            "name": "第四段伤害",
            "param": [
              [
                "32.51%*3",
                "35.18%*3",
                "37.84%*3",
                "41.57%*3",
                "44.24%*3",
                "47.30%*3",
                "51.57%*3",
                "55.83%*3",
                "60.10%*3",
                "64.63%*3",
                "69.96%*3",
                "75.29%*3",
                "80.62%*3",
                "85.95%*3",
                "91.28%*3",
                "96.61%*3",
                "101.94%*3",
                "107.27%*3",
                "112.61%*3",
                "117.94%*3"
              ]
            ]
          },
          "5": {
            "name": "重击·鸣铁伤害",
            "param": [
              [
                "23.34%*3",
                "25.25%*3",
                "27.16%*3",
                "29.84%*3",
                "31.76%*3",
                "33.96%*3",
                "37.02%*3",
                "40.08%*3",
                "43.14%*3",
                "46.39%*3",
                "50.22%*3",
                "54.05%*3",
                "57.87%*3",
                "61.70%*3",
                "65.53%*3",
                "69.35%*3",
                "73.18%*3",
                "77.01%*3",
                "80.83%*3",
                "84.66%*3"
              ]
            ]
          },
          "6": {
            "name": "空中攻击伤害",
            "param": [
              [
                "30.00%*2",
                "32.46%*2",
                "34.92%*2",
                "38.37%*2",
                "40.83%*2",
                "43.66%*2",
                "47.59%*2",
                "51.53%*2",
                "55.47%*2",
                "59.65%*2",
                "64.57%*2",
                "69.49%*2",
                "74.41%*2",
                "79.33%*2",
                "84.25%*2",
                "89.17%*2",
                "94.09%*2",
                "99.01%*2",
                "103.93%*2",
                "108.85%*2"
              ]
            ]
          },
          "7": {
            "name": "闪避反击伤害",
            "param": [
              [
                "33.70%*2",
                "36.47%*2",
                "39.23%*2",
                "43.10%*2",
                "45.86%*2",
                "49.04%*2",
                "53.46%*2",
                "57.88%*2",
                "62.31%*2",
                "67.00%*2",
                "72.53%*2",
                "78.06%*2",
                "83.58%*2",
                "89.11%*2",
                "94.64%*2",
                "100.16%*2",
                "105.69%*2",
                "111.22%*2",
                "116.75%*2",
                "122.27%*2"
              ]
            ]
          },
          "8": {
            "name": "空中闪避反击伤害",
            "param": [
              [
                "30.00%*2",
                "32.46%*2",
                "34.92%*2",
                "38.37%*2",
                "40.83%*2",
                "43.66%*2",
                "47.59%*2",
                "51.53%*2",
                "55.47%*2",
                "59.65%*2",
                "64.57%*2",
                "69.49%*2",
                "74.41%*2",
                "79.33%*2",
                "84.25%*2",
                "89.17%*2",
                "94.09%*2",
                "99.01%*2",
                "103.93%*2",
                "108.85%*2"
              ]
            ]
          },
          "9": {
            "name": "重击·鸣铁耐力消耗",
            "param": [
              [
                "20",
                "20",
                "20",
                "20",
                "20",
                "20",
                "20",
                "20",
                "20",
                "20",
                "20",
                "20",
                "20",
                "20",
                "20",
                "20",
                "20",
                "20",
                "20",
                "20"
              ]
            ]
          },
          "10": {
            "name": "空中攻击耐力消耗",
            "param": [
              [
                "30",
                "30",
                "30",
                "30",
                "30",
                "30",
                "30",
                "30",
                "30",
                "30",
                "30",
                "30",
                "30",
                "30",
                "30",
                "30",
                "30",
                "30",
                "30",
                "30"
              ]
            ]
          },
          "11": {
            "name": "空中闪避反击耐力消耗",
            "param": [
              [
                "30",
                "30",
                "30",
                "30",
                "30",
                "30",
                "30",
                "30",
                "30",
                "30",
                "30",
                "30",
                "30",
                "30",
                "30",
                "30",
                "30",
                "30",
                "30",
                "30"
              ]
            ]
          },
          "12": {
            "name": "重击·烁雷·后撤伤害",
            "param": [
              [
                "27.00%",
                "29.22%",
                "31.43%",
                "34.53%",
                "36.75%",
                "39.29%",
                "42.84%",
                "46.38%",
                "49.92%",
                "53.68%",
                "58.11%",
                "62.54%",
                "66.97%",
                "71.40%",
                "75.82%",
                "80.25%",
                "84.68%",
                "89.11%",
                "93.54%",
                "97.96%"
              ]
            ]
          },
          "13": {
            "name": "重击·烁雷·旋切伤害",
            "param": [
              [
                "71.28%*3",
                "77.13%*3",
                "82.97%*3",
                "91.16%*3",
                "97.00%*3",
                "103.72%*3",
                "113.08%*3",
                "122.43%*3",
                "131.78%*3",
                "141.72%*3",
                "153.41%*3",
                "165.10%*3",
                "176.79%*3",
                "188.48%*3",
                "200.17%*3",
                "211.86%*3",
                "223.55%*3",
                "235.24%*3",
                "246.93%*3",
                "258.62%*3"
              ]
            ]
          },
          "14": {
            "name": "重击·烁雷·升拳伤害",
            "param": [
              [
                "90.00%*2",
                "97.38%*2",
                "104.76%*2",
                "115.10%*2",
                "122.48%*2",
                "130.96%*2",
                "142.77%*2",
                "154.58%*2",
                "166.39%*2",
                "178.93%*2",
                "193.69%*2",
                "208.45%*2",
                "223.21%*2",
                "237.97%*2",
                "252.73%*2",
                "267.49%*2",
                "282.25%*2",
                "297.01%*2",
                "311.77%*2",
                "326.53%*2"
              ]
            ]
          },
          "15": {
            "name": "闪避反击·重击·鸣铁伤害",
            "param": [
              [
                "23.34%*3",
                "25.25%*3",
                "27.16%*3",
                "29.84%*3",
                "31.76%*3",
                "33.96%*3",
                "37.02%*3",
                "40.08%*3",
                "43.14%*3",
                "46.39%*3",
                "50.22%*3",
                "54.05%*3",
                "57.87%*3",
                "61.70%*3",
                "65.53%*3",
                "69.35%*3",
                "73.18%*3",
                "77.01%*3",
                "80.83%*3",
                "84.66%*3"
              ]
            ]
          },
          "16": {
            "name": "闪避反击·烁雷·后撤伤害",
            "param": [
              [
                "27.00%",
                "29.22%",
                "31.43%",
                "34.53%",
                "36.75%",
                "39.29%",
                "42.84%",
                "46.38%",
                "49.92%",
                "53.68%",
                "58.11%",
                "62.54%",
                "66.97%",
                "71.40%",
                "75.82%",
                "80.25%",
                "84.68%",
                "89.11%",
                "93.54%",
                "97.96%"
              ]
            ]
          },
          "17": {
            "name": "重击·烁雷·旋切耐力消耗",
            "param": [
              [
                "20",
                "20",
                "20",
                "20",
                "20",
                "20",
                "20",
                "20",
                "20",
                "20",
                "20",
                "20",
                "20",
                "20",
                "20",
                "20",
                "20",
                "20",
                "20",
                "20"
              ]
            ]
          },
          "18": {
            "name": "重击·烁雷·升拳耐力消耗",
            "param": [
              [
                "20",
                "20",
                "20",
                "20",
                "20",
                "20",
                "20",
                "20",
                "20",
                "20",
                "20",
                "20",
                "20",
                "20",
                "20",
                "20",
                "20",
                "20",
                "20",
                "20"
              ]
            ]
          }
        }
      }
    },
    "2": {
      "skill": {
        "name": "斩锋",
        "desc": "奥古斯塔挥刀跳劈，造成导电伤害。",
        "param": [],
        "type": "共鸣技能",
        "level": {
          "20": {
            "name": "技能伤害",
            "param": [
              [
                "110.00%*3",
                "119.02%*3",
                "128.04%*3",
                "140.67%*3",
                "149.69%*3",
                "160.07%*3",
                "174.50%*3",
                "188.93%*3",
                "203.36%*3",
                "218.70%*3",
                "236.74%*3",
                "254.78%*3",
                "272.82%*3",
                "290.86%*3",
                "308.90%*3",
                "326.94%*3",
                "344.98%*3",
                "363.02%*3",
                "381.06%*3",
                "399.10%*3"
              ]
            ]
          },
          "21": {
            "name": "冷却时间",
            "param": [
              [
                "15",
                "15",
                "15",
                "15",
                "15",
                "15",
                "15",
                "15",
                "15",
                "15",
                "15",
                "15",
                "15",
                "15",
                "15",
                "15",
                "15",
                "15",
                "15",
                "15"
              ]
            ]
          },
          "22": {
            "name": "回复协奏能量",
            "param": [
              [
                "10",
                "10",
                "10",
                "10",
                "10",
                "10",
                "10",
                "10",
                "10",
                "10",
                "10",
                "10",
                "10",
                "10",
                "10",
                "10",
                "10",
                "10",
                "10",
                "10"
              ]
            ]
          }
        }
      }
    },
    "3": {
      "skill": {
        "name": "至日的征伐",
        "desc": "共鸣解放·誓锋不殒\n短按共鸣解放松开时可施放该技能，奥古斯塔发动横扫斩击，造成导电伤害，此次伤害为重击伤害。\n\n共鸣解放·赫日威临\n当存在{0}层【威慑】时，长按共鸣解放可施放共鸣解放·赫日威临。共鸣解放·赫日威临施放时不消耗共鸣能量，而是消耗{0}层【威慑】。\n·施放共鸣解放·赫日威临时，展开王之界域，并且进入{1}秒的俯首之刻，俯首之刻持续期间时间暂时停止，不能切换角色，仅能施放赫日威临·烈阳、赫日威临·不朽者之肃、闪避，处于空中状态时可以施放空中攻击。\n·俯首之刻期间，短按普攻或长按普攻可施放赫日威临·烈阳。可在水面行走且不消耗耐力。\n·若进行场景、玩法、或功能交互时，将强制结束俯首之刻，且不会自动施放赫日威临·不朽者之肃。\n\n赫日威临·烈阳\n造成导电伤害，此伤害为重击伤害。施放{2}次赫日威临·烈阳后，短按普攻或共鸣解放可施放赫日威临·不朽者之肃。\n\n赫日威临·不朽者之肃\n造成导电伤害，此次伤害为重击伤害。施放赫日威临·不朽者之肃时解除俯首之刻，技能结束时消耗全部的【以众愿为冕】，且队伍中除奥古斯塔外的其他角色离场。\n·俯首之刻结束时自动施放赫日威临·不朽者之肃。\n·俯首之刻持续期间可长按共鸣解放，提前施放赫日威临·不朽者之肃。\n\n王之界域\n·王之界域持续{3}秒。\n·王之界域存在时：队伍中角色施放变奏技能时，获得基于奥古斯塔最大生命{4}+{5}的护盾，不可叠加，持续{6}秒。该护盾在切换至其他角色时不会继承。\n\n【威慑】获取方式\n【威慑】上限为2层。\n·施放共鸣技能·不败恒阳·落袭时，奥古斯塔获得1层【威慑】。\n·队友处于奥古斯塔延奏技能·不屈的战歌的效果期间，施放延奏技能时，奥古斯塔获得1层【威慑】。",
        "param": [
          "2",
          "7",
          "9",
          "30",
          "5%",
          "650",
          "10"
        ],
        "type": "共鸣解放",
        "level": {
          "30": {
            "name": "共鸣解放·誓锋不殒伤害",
            "param": [
              [
                "16.59%*2+66.36%*3+16.59%*2+287.56%",
                "17.96%*2+71.81%*3+17.96%*2+311.14%",
                "19.32%*2+77.25%*3+19.32%*2+334.72%",
                "21.22%*2+84.87%*3+21.22%*2+367.74%",
                "22.58%*2+90.31%*3+22.58%*2+391.32%",
                "24.15%*2+96.57%*3+24.15%*2+418.43%",
                "26.32%*2+105.27%*3+26.32%*2+456.16%",
                "28.50%*2+113.98%*3+28.50%*2+493.89%",
                "30.67%*2+122.68%*3+30.67%*2+531.62%",
                "32.99%*2+131.94%*3+32.99%*2+571.7%",
                "35.71%*2+142.82%*3+35.71%*2+618.86%",
                "38.43%*2+153.70%*3+38.43%*2+666.02%",
                "41.15%*2+164.58%*3+41.15%*2+713.18%",
                "43.87%*2+175.47%*3+43.87%*2+760.34%",
                "46.59%*2+186.35%*3+46.59%*2+807.5%",
                "49.31%*2+197.23%*3+49.31%*2+854.66%",
                "52.03%*2+208.12%*3+52.03%*2+901.82%",
                "54.75%*2+219.00%*3+54.75%*2+948.98%",
                "57.47%*2+229.88%*3+57.47%*2+996.14%",
                "60.20%*2+240.77%*3+60.20%*2+1043.3%"
              ]
            ]
          },
          "31": {
            "name": "赫日威临·烈阳伤害",
            "param": [
              [
                "60.00%",
                "64.92%",
                "69.84%",
                "76.73%",
                "81.65%",
                "87.31%",
                "95.18%",
                "103.05%",
                "110.93%",
                "119.29%",
                "129.13%",
                "138.97%",
                "148.81%",
                "158.65%",
                "168.49%",
                "178.33%",
                "188.17%",
                "198.01%",
                "207.85%",
                "217.69%"
              ]
            ]
          },
          "32": {
            "name": "赫日威临·不朽者之肃伤害",
            "param": [
              [
                "120.00%+450.00%+3.00%*10",
                "129.84%+486.90%+3.25%*10",
                "139.68%+523.80%+3.50%*10",
                "153.46%+575.46%+3.84%*10",
                "163.30%+612.36%+4.09%*10",
                "174.62%+654.80%+4.37%*10",
                "190.36%+713.84%+4.76%*10",
                "206.10%+772.88%+5.16%*10",
                "221.85%+831.92%+5.55%*10",
                "238.58%+894.65%+5.97%*10",
                "258.26%+968.45%+6.46%*10",
                "277.94%+1042.25%+6.95%*10",
                "297.62%+1116.05%+7.45%*10",
                "317.30%+1189.85%+7.94%*10",
                "336.98%+1263.65%+8.43%*10",
                "356.66%+1337.45%+8.92%*10",
                "376.34%+1411.25%+9.41%*10",
                "396.02%+1485.05%+9.91%*10",
                "415.70%+1558.85%+10.40%*10",
                "435.38%+1632.65%+10.89%*10"
              ]
            ]
          },
          "33": {
            "name": "共鸣解放·誓锋不殒冷却时间",
            "param": [
              [
                "25",
                "25",
                "25",
                "25",
                "25",
                "25",
                "25",
                "25",
                "25",
                "25",
                "25",
                "25",
                "25",
                "25",
                "25",
                "25",
                "25",
                "25",
                "25",
                "25"
              ]
            ]
          },
          "34": {
            "name": "共鸣解放·誓锋不殒消耗共鸣能量",
            "param": [
              [
                "125",
                "125",
                "125",
                "125",
                "125",
                "125",
                "125",
                "125",
                "125",
                "125",
                "125",
                "125",
                "125",
                "125",
                "125",
                "125",
                "125",
                "125",
                "125",
                "125"
              ]
            ]
          },
          "35": {
            "name": "共鸣解放·誓锋不殒回复协奏能量",
            "param": [
              [
                "20",
                "20",
                "20",
                "20",
                "20",
                "20",
                "20",
                "20",
                "20",
                "20",
                "20",
                "20",
                "20",
                "20",
                "20",
                "20",
                "20",
                "20",
                "20",
                "20"
              ]
            ]
          },
          "36": {
            "name": "共鸣解放·赫日威临冷却时间",
            "param": [
              [
                "25",
                "25",
                "25",
                "25",
                "25",
                "25",
                "25",
                "25",
                "25",
                "25",
                "25",
                "25",
                "25",
                "25",
                "25",
                "25",
                "25",
                "25",
                "25",
                "25"
              ]
            ]
          },
          "37": {
            "name": "赫日威临·不朽者之肃冷却时间",
            "param": [
              [
                "3",
                "3",
                "3",
                "3",
                "3",
                "3",
                "3",
                "3",
                "3",
                "3",
                "3",
                "3",
                "3",
                "3",
                "3",
                "3",
                "3",
                "3",
                "3",
                "3"
              ]
            ]
          }
        }
      }
    },
    "4": {
      "skill": {
        "name": "荣誉的加护",
        "desc": "奥古斯塔造成伤害时，获得最大生命{0}+{1}的护盾，不可叠加，持续{2}秒，每{3}秒可生效1次。该护盾在切换至其他角色时不会继承。",
        "param": [
          "2.5%",
          "350",
          "5",
          "0.5"
        ],
        "type": "固有技能",
        "level": {}
      }
    },
    "5": {
      "skill": {
        "name": "炽盛决意",
        "desc": "奥古斯塔处于非战斗状态大于{0}秒时，获得如下效果，每{1}秒可生效1次：\n·若【威慑】少于1层，则补至1层。\n·【以众愿为冕】补充至上限。",
        "param": [
          "4",
          "4"
        ],
        "type": "固有技能",
        "level": {}
      }
    },
    "6": {
      "skill": {
        "name": "灼金的巡行",
        "desc": "造成导电伤害。",
        "param": [],
        "type": "变奏技能",
        "level": {
          "38": {
            "name": "技能伤害",
            "param": [
              [
                "50.00%*2",
                "54.10%*2",
                "58.20%*2",
                "63.94%*2",
                "68.04%*2",
                "72.76%*2",
                "79.32%*2",
                "85.88%*2",
                "92.44%*2",
                "99.41%*2",
                "107.61%*2",
                "115.81%*2",
                "124.01%*2",
                "132.21%*2",
                "140.41%*2",
                "148.61%*2",
                "156.81%*2",
                "165.01%*2",
                "173.21%*2",
                "181.41%*2"
              ]
            ]
          },
          "39": {
            "name": "回复协奏能量",
            "param": [
              [
                "10",
                "10",
                "10",
                "10",
                "10",
                "10",
                "10",
                "10",
                "10",
                "10",
                "10",
                "10",
                "10",
                "10",
                "10",
                "10",
                "10",
                "10",
                "10",
                "10"
              ]
            ]
          }
        }
      }
    },
    "7": {
      "skill": {
        "name": "曜阳如我",
        "desc": "共鸣技能·不败恒阳·迅击\n【权炳】满时，奥古斯塔的共鸣技能·斩锋替换为共鸣技能·不败恒阳·迅击，造成导电伤害。\n·技能施放时，短按普攻或共鸣技能，可以施放共鸣技能·不败恒阳·跃空。\n·短时间内被打断则可重新施放共鸣技能·不败恒阳·迅击。\n·一定时间后被打断则可施放共鸣技能·不败恒阳·跃空。\n·可在空中施放。\n\n共鸣技能·不败恒阳·跃空\n造成导电伤害。\n·技能施放时，短按普攻或共鸣技能，可以施放共鸣技能·不败恒阳·落袭。\n·短时间内被打断则可重新施放共鸣技能·不败恒阳·跃空。\n·一定时间后被打断则可施放共鸣技能·不败恒阳·落袭。\n·仅可在空中施放。\n\n共鸣技能·不败恒阳·落袭\n施放时消耗全部的【权炳】，造成导电伤害，此次伤害为重击伤害。\n·施放时，获得1层【威慑】。\n·仅可在空中施放。\n\n闪避反击·不败恒阳·迅击\n【权炳】满时，地面闪避成功后短按共鸣技能，或者空中闪避成功后短按普攻或共鸣技能，可施放闪避反击·不败恒阳·迅击，施放时造成导电伤害，此次伤害为共鸣技能伤害。\n·技能施放时，短按普攻或共鸣技能，可以施放共鸣技能·不败恒阳·跃空。\n·一定时间后被打断则可施放共鸣技能·不败恒阳·跃空。\n\n【权炳】获取规则\n【权炳】上限为{0}点。\n·常态攻击造成伤害时，可以获得【权炳】。\n·施放变奏技能·灼金的巡行时回复{1}【权炳】。\n·施放共鸣技能·斩锋时回复{2}【权炳】。\n·施放共鸣解放·誓锋不殒时回复{3}【权炳】。",
        "param": [
          "100",
          "20%",
          "10%",
          "40%"
        ],
        "type": "共鸣回路",
        "level": {
          "23": {
            "name": "共鸣技能·不败恒阳·迅击伤害",
            "param": [
              [
                "70.00%*2",
                "75.74%*2",
                "81.48%*2",
                "89.52%*2",
                "95.26%*2",
                "101.86%*2",
                "111.05%*2",
                "120.23%*2",
                "129.41%*2",
                "139.17%*2",
                "150.65%*2",
                "162.13%*2",
                "173.61%*2",
                "185.09%*2",
                "196.57%*2",
                "208.05%*2",
                "219.53%*2",
                "231.01%*2",
                "242.49%*2",
                "253.97%*2"
              ]
            ]
          },
          "24": {
            "name": "共鸣技能·不败恒阳·跃空伤害",
            "param": [
              [
                "112.00%+14.00%*2",
                "121.19%+15.15%*2",
                "130.37%+16.30%*2",
                "143.23%+17.91%*2",
                "152.41%+19.06%*2",
                "162.98%+20.38%*2",
                "177.67%+22.21%*2",
                "192.36%+24.05%*2",
                "207.06%+25.89%*2",
                "222.67%+27.84%*2",
                "241.04%+30.13%*2",
                "259.41%+32.43%*2",
                "277.78%+34.73%*2",
                "296.14%+37.02%*2",
                "314.51%+39.32%*2",
                "332.88%+41.61%*2",
                "351.25%+43.91%*2",
                "369.62%+46.21%*2",
                "387.98%+48.50%*2",
                "406.35%+50.80%*2"
              ]
            ]
          },
          "25": {
            "name": "共鸣技能·不败恒阳·落袭伤害",
            "param": [
              [
                "43.55%+391.95%",
                "47.13%+424.09%",
                "50.70%+456.23%",
                "55.70%+501.23%",
                "59.27%+533.37%",
                "63.37%+570.33%",
                "69.09%+621.76%",
                "74.80%+673.18%",
                "80.52%+724.60%",
                "86.59%+779.24%",
                "93.73%+843.52%",
                "100.87%+907.80%",
                "108.01%+972.08%",
                "115.16%+1036.36%",
                "122.30%+1100.64%",
                "129.44%+1164.92%",
                "136.58%+1229.20%",
                "143.72%+1293.48%",
                "150.87%+1357.76%",
                "158.01%+1422.04%"
              ]
            ]
          },
          "26": {
            "name": "空中闪避反击·不败恒阳·迅击伤害",
            "param": [
              [
                "70.00%*2",
                "75.74%*2",
                "81.48%*2",
                "89.52%*2",
                "95.26%*2",
                "101.86%*2",
                "111.05%*2",
                "120.23%*2",
                "129.41%*2",
                "139.17%*2",
                "150.65%*2",
                "162.13%*2",
                "173.61%*2",
                "185.09%*2",
                "196.57%*2",
                "208.05%*2",
                "219.53%*2",
                "231.01%*2",
                "242.49%*2",
                "253.97%*2"
              ]
            ]
          },
          "27": {
            "name": "共鸣技能·不败恒阳·落袭回复协奏能量",
            "param": [
              [
                "7",
                "7",
                "7",
                "7",
                "7",
                "7",
                "7",
                "7",
                "7",
                "7",
                "7",
                "7",
                "7",
                "7",
                "7",
                "7",
                "7",
                "7",
                "7",
                "7"
              ]
            ]
          },
          "28": {
            "name": "共鸣技能·不败恒阳·迅击耐力消耗",
            "param": [
              [
                "10",
                "10",
                "10",
                "10",
                "10",
                "10",
                "10",
                "10",
                "10",
                "10",
                "10",
                "10",
                "10",
                "10",
                "10",
                "10",
                "10",
                "10",
                "10",
                "10"
              ]
            ]
          },
          "29": {
            "name": "共鸣技能·不败恒阳·跃空耐力消耗",
            "param": [
              [
                "10",
                "10",
                "10",
                "10",
                "10",
                "10",
                "10",
                "10",
                "10",
                "10",
                "10",
                "10",
                "10",
                "10",
                "10",
                "10",
                "10",
                "10",
                "10",
                "10"
              ]
            ]
          }
        }
      }
    },
    "8": {
      "skill": {
        "name": "不屈的战歌",
        "desc": "下一位登场角色获得如下效果，持续{0}秒，若切换至其他角色则如下效果提前结束：\n·全伤害加深{1}。\n·施放延奏技能时，让队伍中的奥古斯塔获得{2}层【威慑】与{3}层【以众愿为冕】。\n\n【以众愿为冕】\n每层使导电伤害加成提升{4}，上限为{5}层。共鸣解放·赫日威临·不朽者之肃结束时，清除自身全部的【以众愿为冕】。",
        "param": [
          "14",
          "15%",
          "1",
          "1",
          "15%",
          "1"
        ],
        "type": "延奏技能",
        "level": {}
      }
    },
    "9": {
      "skill": {
        "name": "暴击提升",
        "desc": "暴击提升{0}",
        "param": [
          "1.20%"
        ]
      }
    },
    "10": {
      "skill": {
        "name": "攻击提升",
        "desc": "攻击提升{0}",
        "param": [
          "1.80%"
        ]
      }
    },
    "11": {
      "skill": {
        "name": "攻击提升",
        "desc": "攻击提升{0}",
        "param": [
          "1.80%"
        ]
      }
    },
    "12": {
      "skill": {
        "name": "暴击提升",
        "desc": "暴击提升{0}",
        "param": [
          "1.20%"
        ]
      }
    },
    "13": {
      "skill": {
        "name": "暴击提升",
        "desc": "暴击提升{0}",
        "param": [
          "2.80%"
        ]
      }
    },
    "14": {
      "skill": {
        "name": "攻击提升",
        "desc": "攻击提升{0}",
        "param": [
          "4.20%"
        ]
      }
    },
    "15": {
      "skill": {
        "name": "攻击提升",
        "desc": "攻击提升{0}",
        "param": [
          "4.20%"
        ]
      }
    },
    "16": {
      "skill": {
        "name": "暴击提升",
        "desc": "暴击提升{0}",
        "param": [
          "2.80%"
        ]
      }
    }
  },
  "chains": {
    "1": {
      "name": "于焦壤中蒙垢",
      "desc": "·【以众愿为冕】每层使暴击伤害额外提升{0}。\n·【以众愿为冕】上限提高至{1}层。\n·奥古斯塔施放变奏技能·灼金的巡行时，也可以获得{2}层【以众愿为冕】。\n·共鸣技能·不败恒阳·迅击、共鸣技能·不败恒阳·跃空、共鸣技能·不败恒阳·落袭免疫打断。",
      "param": [
        "15%",
        "2",
        "1"
      ]
    },
    "2": {
      "name": "于血戮中涤尘",
      "desc": "·【以众愿为冕】获得额外效果：每层使暴击提升{0}。\n·奥古斯塔暴击高于{1}时，每多出{2}暴击，奥古斯塔暴击伤害提升{3}，最高可提升{4}暴击伤害。",
      "param": [
        "20%",
        "100%",
        "1%",
        "2%",
        "100%"
      ]
    },
    "3": {
      "name": "于朽腐中砺骨",
      "desc": "以下技能的伤害倍率提升{0}：\n·重击·烁雷·后撤、闪避反击·烁雷·后撤、重击·烁雷·旋切、重击·烁雷·升拳。\n·共鸣技能·不败恒阳·落袭。\n·共鸣解放·赫日威临·烈阳、共鸣解放·赫日威临·不朽者之肃。",
      "param": [
        "25%"
      ]
    },
    "4": {
      "name": "于荣辉中孤行",
      "desc": "施放变奏技能·灼金的巡行时，队伍中的角色的攻击提升{0}，持续{1}秒。",
      "param": [
        "20%",
        "30"
      ]
    },
    "5": {
      "name": "于怒潮中卓立",
      "desc": "固有技能·荣誉的加护获得护盾量提升{0}。",
      "param": [
        "50%"
      ]
    },
    "6": {
      "name": "于耀光中刻名",
      "desc": "·【以众愿为冕】的上限提升至{0}层。\n·奥古斯塔暴击高于{1}时，每多出{2}暴击，奥古斯塔暴击伤害提升{3}，最高可提升{4}暴击伤害。\n·奥古斯塔施放重击·烁雷·旋切、重击·烁雷·升拳时，可以获得{5}层【以众愿为冕】，每{6}秒仅可通过于耀光中刻名的效果获得{8}层【以众愿为冕】。\n·施放重击·烁雷·旋切、重击·烁雷·升拳过程中，会在原地额外引发【怒霆】，造成两次奥古斯塔攻击{7}的导电伤害，此次伤害为重击伤害。",
      "param": [
        "4",
        "150%",
        "1%",
        "2%",
        "50%",
        "2",
        "1",
        "100%",
        "2"
      ]
    }
  },
  "ascensions": {
    "1": [
      {
        "key": 41100051,
        "value": 4
      },
      {
        "key": 2,
        "value": 5000
      }
    ],
    "2": [
      {
        "key": 41400234,
        "value": 3
      },
      {
        "key": 42601300,
        "value": 4
      },
      {
        "key": 41100052,
        "value": 4
      },
      {
        "key": 2,
        "value": 10000
      }
    ],
    "3": [
      {
        "key": 41400234,
        "value": 6
      },
      {
        "key": 42601300,
        "value": 8
      },
      {
        "key": 41100052,
        "value": 8
      },
      {
        "key": 2,
        "value": 15000
      }
    ],
    "4": [
      {
        "key": 41400234,
        "value": 9
      },
      {
        "key": 42601300,
        "value": 12
      },
      {
        "key": 41100053,
        "value": 4
      },
      {
        "key": 2,
        "value": 20000
      }
    ],
    "5": [
      {
        "key": 41400234,
        "value": 12
      },
      {
        "key": 42601300,
        "value": 16
      },
      {
        "key": 41100053,
        "value": 8
      },
      {
        "key": 2,
        "value": 40000
      }
    ],
    "6": [
      {
        "key": 41400234,
        "value": 16
      },
      {
        "key": 42601300,
        "value": 20
      },
      {
        "key": 41100054,
        "value": 4
      },
      {
        "key": 2,
        "value": 80000
      }
    ]
  }
}