{
  "id": 6000069,
  "name": "魔术先生",
  "intensityCode": 0,
  "group": {
    "10": {
      "name": "凌冽决断之心"
    },
    "13": {
      "name": "高天共奏之曲"
    }
  },
  "skill": {
    "desc": "使用声骸技能，召唤魔术先生攻击，造成3段{0}的湮灭伤害。\n技能冷却：{1}秒",
    "simpleDesc": "召唤魔术先生攻击，对敌人造成湮灭伤害。",
    "params": [
      [
        "24.00%",
        "8"
      ],
      [
        "28.80%",
        "8"
      ],
      [
        "33.60%",
        "8"
      ],
      [
        "38.40%",
        "8"
      ],
      [
        "43.20%",
        "8"
      ]
    ]
  }
}